design/src/gates/gates.v
module and2 (
    output wire out,
    input x,
    input y
);
  assign out = x & y;
endmodule


module or2 (
    output wire out,
    input x,
    input y
);
  assign out = x | y;
endmodule

module inv (
    output wire out,
    input x
);
  assign out = !x;
endmodule

module gates (
    input x,
    input y,
    input z,
    output wire out
);
  assign out = (x & y) | z;
endmodule

design/src/gates/gates_tb.v

module gates_tb ();

  reg in1, in2, in3;
  wire oand, oor, inv1, inv2;
  wire result;

  initial begin
    $monitor("input 1: %b input2: %b -> and: %b or: %b inv1: %b inv2: %b circuit: %b", in1, in2,
             oand, oor, inv1, inv2, result);
    in1 = 0;
    in2 = 0;
    in3 = 0;

    #5{in1, in2, in3} = 3'b100;
    #5{in1, in2, in3} = 3'b110;
    #5{in1, in2, in3} = 3'b010;
    #5{in1, in2, in3} = 3'b001;
    #5{in1, in2, in3} = 3'b101;
    #5{in1, in2, in3} = 3'b111;
    #5{in1, in2, in3} = 3'b011;
  end

  and2 U0 (
      .out(oand),
      .x  (in1),
      .y  (in2)
  );
  or2 U1 (
      .out(oor),
      .x  (in1),
      .y  (in2)
  );
  inv U2 (
      .out(inv1),
      .x  (in1)
  );
  inv U3 (
      .out(inv2),
      .x  (in2)
  );
  gates U4 (
      .out(result),
      .x  (in1),
      .y  (in2),
      .z  (in3)
  );


initial begin
    $dumpfile("gates.vcd");
    $dumpvars(0, gates_tb);
end

endmodule

design/src/gates/gates.vcd
$date
	Fri Aug 15 23:05:46 2025
$end
$version
	Icarus Verilog
$end
$timescale
	1s
$end
$scope module gates_tb $end
$var wire 1 ! result $end
$var wire 1 " oor $end
$var wire 1 # oand $end
$var wire 1 $ inv2 $end
$var wire 1 % inv1 $end
$var reg 1 & in1 $end
$var reg 1 ' in2 $end
$var reg 1 ( in3 $end
$scope module U0 $end
$var wire 1 # out $end
$var wire 1 & x $end
$var wire 1 ' y $end
$upscope $end
$scope module U1 $end
$var wire 1 " out $end
$var wire 1 & x $end
$var wire 1 ' y $end
$upscope $end
$scope module U2 $end
$var wire 1 & x $end
$var wire 1 % out $end
$upscope $end
$scope module U3 $end
$var wire 1 ' x $end
$var wire 1 $ out $end
$upscope $end
$scope module U4 $end
$var wire 1 ! out $end
$var wire 1 & x $end
$var wire 1 ' y $end
$var wire 1 ( z $end
$upscope $end
$upscope $end
$enddefinitions $end
$comment Show the parameter values. $end
$dumpall
$end
#0
$dumpvars
0(
0'
0&
1%
1$
0#
0"
0!
$end
#5
1"
0%
1&
#10
1!
1#
0$
1'
#15
0!
0#
1%
0&
#20
0"
1!
1$
0'
1(
#25
1"
0%
1&
#30
1#
0$
1'
#35
0#
1%
0&
