design/src/mux/decoder.v
module decoder (
    output [1:0] out,
    input sel,
    input enable
);
  wire [1:0] med;
  and (med[0], ~sel);
  and (med[1], sel);
  bufif1 (out[0], med[0], enable);
  bufif1 (out[1], med[1], enable);
endmodule

module decoder4 (
    output [3:0] out,
    input [1:0] sel,
    input enable
);
  wire [3:0] med;
  and (med[0], ~sel[0], ~sel[1]);
  and (med[1], sel[0], ~sel[1]);
  and (med[2], ~sel[0], sel[1]);
  and (med[3], sel[0], sel[1]);
  bufif1 (out[0], med[0], enable);
  bufif1 (out[1], med[1], enable);
  bufif1 (out[2], med[2], enable);
  bufif1 (out[3], med[3], enable);
endmodule

design/src/mux/encoder.v
module encoder (
    output out,
    input [1:0] in,
    input enable
);
  assign out = enable ? in[1] : 1'bZ;
endmodule

module encoder4 (
    output [1:0] out,
    input [3:0] in,
    input enable
);
  assign out[0] = enable ? in[1] | in[3] : 1'bZ;
  assign out[1] = enable ? ~in[1] & ~in[0] : 1'bZ;
endmodule

design/src/mux/demux.v
module demux (
    output [1:0] out,
    input in,
    input sel
);
  assign out = in << sel;
endmodule

module demux4 (
    output [3:0] out,
    input in,
    input [1:0] sel
);
  assign out = in << ((sel[1] * 2) + sel[0]);
endmodule

design/src/mux/mux.v

module mux (
    output out,
    input [1:0] in,
    input sel
);
  assign out = in[sel];
endmodule


module mux4 (
    output out,
    input [3:0] in,
    input [1:0] sel
);
  wire med1, med2;
  mux U0 (
      .out(med1),
      .in (in[1:0]),
      .sel(sel[0])
  );
  mux U1 (
      .out(med2),
      .in (in[3:2]),
      .sel(sel[0])
  );
  mux U3 (
      .out(out),
      .in ({med2, med1}),
      .sel(sel[1])
  );
endmodule

design/src/mux/tb.v
module tb ();
  reg [1:0] mux_in;
  reg mux_sel;
  wire mux_out;

  reg [3:0] mux4_in;
  reg [1:0] mux4_sel;
  wire mux4_out;

  reg demux_in;
  reg demux_sel;
  wire [1:0] demux_out;

  reg demux4_in;
  reg [1:0] demux4_sel;
  wire [3:0] demux4_out;

  reg [1:0] enc_in;
  reg enc_enable;
  wire enc_out;

  reg [3:0] enc4_in;
  reg enc4_enable;
  wire [1:0] enc4_out;

  reg dec_inp, dec_ena;
  wire [1:0] dec_out;

  reg [1:0] dec4_inp;
  reg dec4_ena;
  wire [3:0] dec4_out;

  initial begin
    $display("MUX TESTBENCH");
    mux_in  = 2'b00;
    mux_sel = 1'b0;
    $monitor("2:1 MUX :: in = %2b, sel = %b, out = %b", mux_in, mux_sel, mux_out);

    #5{mux_in, mux_sel} = 3'b001;
    #5{mux_in, mux_sel} = 3'b010;
    #5{mux_in, mux_sel} = 3'b011;
    #5{mux_in, mux_sel} = 3'b100;
    #5{mux_in, mux_sel} = 3'b101;
    #5{mux_in, mux_sel} = 3'b110;
    #5{mux_in, mux_sel} = 3'b111;
    #5 mux4_in = 4'b0000;
    mux4_sel = 2'b00;
    $monitor("4:1 MUX :: in = %4b, sel = %2b, out = %b", mux4_in, mux4_sel, mux4_out);

    #5{mux4_in, mux4_sel} = 6'b000100;
    #5{mux4_in, mux4_sel} = 6'b011101;
    #5{mux4_in, mux4_sel} = 6'b101110;
    #5{mux4_in, mux4_sel} = 6'b010011;
    #5{mux4_in, mux4_sel} = 6'b010100;
    #5{mux4_in, mux4_sel} = 6'b111001;
    #5{mux4_in, mux4_sel} = 6'b011110;
    #5 $display("DEMUX TESTBENCH");

    {demux_in, demux_sel} = 2'b00;
    $monitor("1:2 DEMUX :: in = %b, sel = %b, out = %2b", demux_in, demux_sel, demux_out);

    #5{demux_in, demux_sel} = 2'b01;
    #5{demux_in, demux_sel} = 2'b10;
    #5{demux_in, demux_sel} = 2'b11;
    #5{demux4_in, demux4_sel} = 3'b000;
    $monitor("1:4 DEMUX :: in = %b, sel = %2b, out = %4b", demux4_in, demux4_sel, demux4_out);

    #5{demux4_in, demux4_sel} = 3'b001;
    #5{demux4_in, demux4_sel} = 3'b010;
    #5{demux4_in, demux4_sel} = 3'b011;
    #5{demux4_in, demux4_sel} = 3'b100;
    #5{demux4_in, demux4_sel} = 3'b101;
    #5{demux4_in, demux4_sel} = 3'b110;
    #5{demux4_in, demux4_sel} = 3'b111;
    #5 $display("ENCODER TESTBENCH");

    enc_enable = 1'b0;
    $monitor("2:1 ENCODER :: enable = %b, in = %2b, out = %b", enc_enable, enc_in, enc_out);

    #5{enc_enable, enc_in} = 3'b101;
    #5{enc_enable, enc_in} = 3'b110;
    #5 enc4_enable = 1'b0;
    $monitor("4:1 ENCODER :: enable = %b, in = %4b, out = %2b", enc4_enable, enc4_in, enc4_out);

    #5{enc4_enable, enc4_in} = 5'b10001;
    #5{enc4_enable, enc4_in} = 5'b10010;
    #5{enc4_enable, enc4_in} = 5'b10100;
    #5{enc4_enable, enc4_in} = 5'b11000;
    #5 $display("DECODER TESTBENCH");

    dec_ena = 1'b0;
    $monitor("1:2 DECODER :: enable = %b, in = %b, out = %2b", dec_ena, dec_inp, dec_out);

    #5{dec_ena, dec_inp} = 2'b10;
    #5{dec_ena, dec_inp} = 2'b11;
    #5 dec4_ena = 1'b0;
    $monitor("2:4 DECODER :: enable = %b, in = %2b, out = %4b", dec4_ena, dec4_inp, dec4_out);

    #5{dec4_ena, dec4_inp} = 3'b100;
    #5{dec4_ena, dec4_inp} = 3'b101;
    #5{dec4_ena, dec4_inp} = 3'b110;
    #5{dec4_ena, dec4_inp} = 3'b111;
    #30 $finish(0);
  end

  mux U0 (
      .out(mux_out),
      .in (mux_in),
      .sel(mux_sel)
  );

  mux4 U1 (
      .out(mux4_out),
      .in (mux4_in),
      .sel(mux4_sel)
  );

  demux U2 (
      .out(demux_out),
      .in (demux_in),
      .sel(demux_sel)
  );

  demux4 U3 (
      .out(demux4_out),
      .in (demux4_in),
      .sel(demux4_sel)
  );

  encoder U4 (
      .out(enc_out),
      .in(enc_in),
      .enable(enc_enable)
  );

  encoder4 U5 (
      .out(enc4_out),
      .in(enc4_in),
      .enable(enc4_enable)
  );

  decoder U6 (
      .out(dec_out),
      .sel(dec_inp),
      .enable(dec_ena)
  );

  decoder4 U7 (
      .out(dec4_out),
      .sel(dec4_inp),
      .enable(dec4_ena)
  );

  initial begin
    $dumpfile("mux.vcd");
    $dumpvars(0, tb);
  end


endmodule

design/src/mux/mux.vcd
$date
	Sat Aug 30 13:43:52 2025
$end
$version
	Icarus Verilog
$end
$timescale
	1s
$end
$scope module tb $end
$var wire 1 ! mux_out $end
$var wire 1 " mux4_out $end
$var wire 1 # enc_out $end
$var wire 2 $ enc4_out [1:0] $end
$var wire 2 % demux_out [1:0] $end
$var wire 4 & demux4_out [3:0] $end
$var wire 2 ' dec_out [1:0] $end
$var wire 4 ( dec4_out [3:0] $end
$var reg 1 ) dec4_ena $end
$var reg 2 * dec4_inp [1:0] $end
$var reg 1 + dec_ena $end
$var reg 1 , dec_inp $end
$var reg 1 - demux4_in $end
$var reg 2 . demux4_sel [1:0] $end
$var reg 1 / demux_in $end
$var reg 1 0 demux_sel $end
$var reg 1 1 enc4_enable $end
$var reg 4 2 enc4_in [3:0] $end
$var reg 1 3 enc_enable $end
$var reg 2 4 enc_in [1:0] $end
$var reg 4 5 mux4_in [3:0] $end
$var reg 2 6 mux4_sel [1:0] $end
$var reg 2 7 mux_in [1:0] $end
$var reg 1 8 mux_sel $end
$scope module U0 $end
$var wire 2 9 in [1:0] $end
$var wire 1 8 sel $end
$var wire 1 ! out $end
$upscope $end
$scope module U1 $end
$var wire 4 : in [3:0] $end
$var wire 2 ; sel [1:0] $end
$var wire 1 " out $end
$var wire 1 < med2 $end
$var wire 1 = med1 $end
$scope module U0 $end
$var wire 2 > in [1:0] $end
$var wire 1 ? sel $end
$var wire 1 = out $end
$upscope $end
$scope module U1 $end
$var wire 2 @ in [1:0] $end
$var wire 1 A sel $end
$var wire 1 < out $end
$upscope $end
$scope module U3 $end
$var wire 2 B in [1:0] $end
$var wire 1 C sel $end
$var wire 1 " out $end
$upscope $end
$upscope $end
$scope module U2 $end
$var wire 1 / in $end
$var wire 1 0 sel $end
$var wire 2 D out [1:0] $end
$upscope $end
$scope module U3 $end
$var wire 1 - in $end
$var wire 2 E sel [1:0] $end
$var wire 4 F out [3:0] $end
$upscope $end
$scope module U4 $end
$var wire 1 3 enable $end
$var wire 2 G in [1:0] $end
$var wire 1 # out $end
$upscope $end
$scope module U5 $end
$var wire 1 1 enable $end
$var wire 4 H in [3:0] $end
$var wire 2 I out [1:0] $end
$upscope $end
$scope module U6 $end
$var wire 1 + enable $end
$var wire 1 , sel $end
$var wire 2 J out [1:0] $end
$var wire 2 K med [1:0] $end
$upscope $end
$scope module U7 $end
$var wire 1 ) enable $end
$var wire 2 L sel [1:0] $end
$var wire 4 M out [3:0] $end
$var wire 4 N med [3:0] $end
$upscope $end
$upscope $end
$enddefinitions $end
$comment Show the parameter values. $end
$dumpall
$end
#0
$dumpvars
bx N
bx M
bx L
bx K
bx J
bx I
bx H
bx G
bx F
bx E
bx D
xC
bx B
xA
bx @
x?
bx >
x=
x<
bx ;
bx :
b0 9
08
b0 7
bx 6
bx 5
bx 4
x3
bx 2
x1
x0
x/
bx .
x-
x,
x+
bx *
x)
bx (
bx '
bx &
bx %
bx $
x#
x"
0!
$end
#5
18
#10
1!
b1 7
b1 9
08
#15
0!
18
#20
b10 7
b10 9
0!
08
#25
1!
18
#30
b11 7
b11 9
1!
08
#35
18
#40
0"
0=
0?
b0 B
0<
0A
0C
b0 >
b0 @
b0 6
b0 ;
b0 5
b0 :
#45
1"
b1 B
1=
b1 >
b1 5
b1 :
#50
b11 >
b1 @
1"
b1 B
1=
1?
1A
b111 5
b111 :
b1 6
b1 ;
#55
b10 @
0?
b1 B
0<
0A
0"
1C
b1011 5
b1011 :
b10 6
b10 ;
#60
0=
b0 >
b1 @
1?
0"
b0 B
0<
1A
b100 5
b100 :
b11 6
b11 ;
#65
1"
1=
b1 >
0?
b11 B
1<
0A
0C
b101 5
b101 :
b0 6
b0 ;
#70
b10 >
b11 @
1"
1=
1?
b11 B
1<
1A
b1110 5
b1110 :
b1 6
b1 ;
#75
b11 >
b1 @
b11 B
1=
0?
0A
1C
b111 5
b111 :
b10 6
b10 ;
#80
0/
b0 %
b0 D
00
#85
10
#90
b1 %
b1 D
1/
00
#95
b10 %
b10 D
10
#100
b0 &
b0 F
0-
b0 .
b0 E
#105
b1 .
b1 E
#110
b10 .
b10 E
#115
b11 .
b11 E
#120
b1 &
b1 F
1-
b0 .
b0 E
#125
b10 &
b10 F
b1 .
b1 E
#130
b100 &
b100 F
b10 .
b10 E
#135
b1000 &
b1000 F
b11 .
b11 E
#140
z#
03
#145
0#
13
b1 4
b1 G
#150
1#
b10 4
b10 G
#155
bz $
bz I
01
#160
b0 $
b0 I
11
b1 2
b1 H
#165
b1 $
b1 I
b10 2
b10 H
#170
b10 $
b10 I
b100 2
b100 H
#175
b11 $
b11 I
b1000 2
b1000 H
#180
bz '
bz J
0+
#185
b1 K
b1 '
b1 J
1+
0,
#190
b10 '
b10 J
b10 K
1,
#195
bz (
bz M
0)
#200
b1 N
b1 (
b1 M
1)
b0 *
b0 L
#205
b10 (
b10 M
b10 N
b1 *
b1 L
#210
b100 (
b100 M
b100 N
b10 *
b10 L
#215
b1000 (
b1000 M
b1000 N
b11 *
b11 L
